{
    "BGP": {
      "BGPAsn": 0,
      "RouterID": "Loopback0",
      "IPv4Network": [
        "P2P",
        "Loopback",
        "BMC",
        "HNVPA",
        "Infrastructure",
        "Tenant",
        "L3Forward"
      ],
      "IPv4Neighbor": [
        {
          "SwitchRelation": "SwitchUplink",
          "Description": "P2P_Border",
          "NeighborAsn": 0,
          "NeighborIPAddress": "P2P_Border",
          "PrefixList": [
            {
              "Name": "ExternalPrefix",
              "Direction": "in"
            },
            {
              "Name": "ExternalPrefix",
              "Direction": "out"
            }
          ],
          "RemovePrivateAS": true,
          "Shutdown": false
        },
        {
          "SwitchRelation": "SwitchPeer",
          "Description": "P2P_IBGP",
          "NbrPassword": "PASSWORD",
          "NeighborAsn": 0,
          "NeighborIPAddress": "P2P_IBGP",
          "PrefixList": [],
          "Shutdown": false
        },
        {
          "SwitchRelation": "SwitchDownlink",
          "Description": "MUX",
          "NeighborAsn": 0,
          "NeighborIPAddress": "HNVPA",
          "PrefixList": [
            {
              "Name": "DefaultRoute",
              "Direction": "out"
            }
          ],
          "UpdateSource": "Loopback0",
          "LocalAS": "64512",
          "EBGPMultiHop": 3,
          "Shutdown": false
        }
      ]
    },
    "Static": [
      {
        "DstIPAddress": "Tenant0",
        "NextHop": "null 0",
        "Name": "Tenant0"
      },
      {
        "DstIPAddress": "Tenant1",
        "NextHop": "null 0",
        "Name": "Tenant1"
      },
      {
        "DstIPAddress": "Any",
        "NextHop": "",
        "Name": "P2P_TORX_To_Border1/TORX"
      },
      {
        "DstIPAddress": "Any",
        "NextHop": "",
        "Name": "P2P_TORX_To_Border2/TORX"
      }
    ],
    "PrefixList": [
      {
        "Name": "ExternalPrefix",
        "Config": [
          {
            "Idx": 1,
            "Action": "deny",
            "Description":"Storage",
            "Network": "Storage",
            "Operation": "le",
            "Prefix": 32
          },
          {
            "Idx": 2,
            "Action": "deny",
            "Description":"Tenant",
            "Network": "Tenant",
            "Operation": "le",
            "Prefix": 32
          },
          {
            "Idx": 3,
            "Action": "permit",
            "Description":"Any",
            "Network": "Any",
            "Operation": "le",
            "Prefix": 32
          }
        ]
      },
      {
        "Name": "DefaultRoute",
        "Config": [
          {
            "Idx": 1,
            "Action": "permit",
            "Description":"Any",
            "Network": "Any",
            "Operation": "",
            "Prefix": 0
          },
          {
            "Idx": 2,
            "Action": "deny",
            "Description":"Any",
            "Network": "Any",
            "Operation": "le",
            "Prefix": 32
          }
        ]
      }
    ]
  }